{
  "posts": [
    {
      "slug": "360-marketing-strategy-full-guide",
      "title": "360° Marketing Strategy Full Guide (And Why Businesses Have Collapsed Without It)",
      "author": "Brands Light Digital",
      "date": "2025-08-10",
      "tags": [
        "Marketing Strategy",
        "Omnichannel",
        "Growth"
      ],
      "excerpt": "A practical, end‑to‑end guide to 360° marketing: pillars, steps, mistakes to avoid, and why brands fail without it.",
      "coverImage": "https://images.unsplash.com/photo-1556157382-97eda2d62296?q=80&w=1600&auto=format&fit=crop",
      "readingTime": 9,
      "contentHtml": "<p>In this hectic pace of the cyber era, competition is intense, consumers' attention spans are shorter than ever, and losing one's way in cyberspace has never been simpler. It is here that successful companies never put all their eggs in a single basket — they take a 360° marketing approach. Brands Light Digital has seen firsthand how a full-board strategy can make startups, small companies, and even large corporations top-of-the-mind brands.</br>This whole digital marketing strategy will walk you through what 360° marketing is, why it is revolutionary and new, and how to create a plan that not only saves your company, but thrives.</p><h2>What is a 360° Marketing Strategy</h2><p>Consumer 360° strategy is a comprehensive consumer strategy that puts your brand in front of your consumers, keeps them there, and engages them at each point of interaction where your consumers are engaging with you. In contrast to the previous mind set in marketing where one or two points of interaction were used, a consumer 360° strategy tackles the whole wheel — offline, online, social, search, content, advertising, etc. — as a whole. </br>It's not being everywhere, but making an invisible, branded packaging experience that trusts and converts.</p><h2>Why Businesses Fail Without a 360° Marketing Strategy</h2><p>Most companies are so one-dimensional about having either a single channel of advertising, say just social media alone or just pay-per-click advertising alone. That is how it will be in the short term, not in the long run. Those are reasons why your company is failing when it is not a 360° end-to-end process</p><ul><li><strong>Consistency of Message - </strong> Your customers are confused if your voice, appearance, or promotions vary on each site.</li><li><strong>Missed opportunities - </strong> Advertising on one site equals losing other potential prospects.</li><li><strong>Poor brand recall - </strong>  Companies with inconsistent consistencies across touchpoints never stay top-of-mind.</li><li><strong>Unbalanced ROI - </strong> Ad cost spent on too much advertising or doing organic work only trying out to lead to escalating costs.</li><li><strong>Competitors win trust - </strong> If your competitors are everywhere and you’re not, they’ll win your audience’s trust.</li></ul><p>In short, without 360° marketing, companies will get lost in the current hectic marketplace.</p><h2>The Pillars of a 360° Marketing Strategy</h2><pAn effective 360° strategy is grounded on different pillars that support each other:</p><ol><li><strong>Branding & Identity</strong> – Your anchor is your brand. Your secure identity with fewer logo, brand story, and messaging is that it simplifies everything.</li><li><strong>Content Marketing</strong> – Blogs, videos, tweets, infographics — content convinces and informs your people. Good content builds trust and optimizes SEO as well.</li><li><strong>SEO</strong> – Research, on‑page, links; lets your content be discovered.</li><li><strong>Social Media</strong> – Presence and community across platforms.</li><li><strong>PPC & Social Ads</strong> – Scalable reach, measurable ROI.</li><li><strong>Email</strong> – Leads, retention, repeat sales.</li><li><strong>Web UX</strong> – Fast, credible, conversion‑focused site.</li><li><strong>Analytics</strong> – Track, learn, optimize.</li></ol><h2>Steps to Build Your 360° Plan</h2><ol><li><strong>Define goals & audience</strong>.</li><li><strong>Build brand foundation</strong> – visual identity, tone, story.</li><li><strong>Map customer journey</strong> – awareness to retention.</li><li><strong>Pick right channels</strong> – not everything, only what fits.</li><li><strong>Create great content</strong> – fuels every channel.</li><li><strong>Align offline & online</strong> – consistent experience.</li><li><strong>Measure & optimize</strong> – decisions from data.</li></ol><h2>Case Study (Theoretical)</h2><p><em>New fashion brand.</em> Only Instagram → minor sales then stall. With 360°: SEO, Google Ads, email, blog, reels, strong branding → higher visibility, trust, and steady growth.</p><h2>Benefits</h2><ul><li>Greater recall & engagement</li><li>Better ROI via channel synergy</li><li>Scalable system</li><li>Consistency across touchpoints</li><li>Competitive advantage</li></ul><h2>Common Mistakes</h2><ul><li>Disjointed voice across SEO/PPC</li><li>No testing</li><li>Too many channels without focus</li><li>No retention plan</li></ul><h2>Future</h2><p>AI, automation, and personalization will drive hyper‑relevant, omnichannel experiences. Brands that adopt end‑to‑end thinking stay ahead.</p><h2>Final Thoughts</h2><p>360° marketing isn’t hype. It’s how modern customers discover and trust brands. Brands Light Digital integrates branding, content, SEO, ads, and design into one growth machine. Ready to map your 360° plan?</p>"
    },
    {
      "slug": "digital-agency-vs-in-house-roi-2025",
      "title": "Digital Agency vs. In‑House Marketing: Which one is Buying Smarter ROI in 2025?",
      "author": "Brands Light Digital",
      "date": "2025-08-10",
      "tags": [
        "ROI",
        "Agency vs In‑House",
        "2025"
      ],
      "excerpt": "A practical comparison of in‑house teams vs digital agencies for ROI in 2025, with pros/cons and a side‑by‑side table.",
      "coverImage": "/images/blogimage2.png",
      "readingTime": 8,
      "contentHtml": "<p>With the ubiquitous digital era in sight, businesses are faced with a landmark decision: employ the services of a digital marketing agency or maintain an in‑house marketing department. Each option has its advantages and disadvantages, and it has a cost associated with it.</p><p>With 2025 looking to be the most competitive and technologically advanced year on record, the right strategy is what you need by way of return on investment (ROI). Brands Light Digital has partnered with startups, small businesses, and large corporations, and we understand that the decision here can make or break long‑term growth.</p><p>In this guide, we will compare in‑house teams with digital marketing agencies ROI so you can decide on the best approach for your goals.</p><h2>Why ROI Matters More Than Ever in 2025</h2><p>ROI is more than cost over revenue. In marketing, ROI means visibility, brand recall, lead generation, customer acquisition, and retention for the long haul.</p><p>With each spend uptick, algorithms change, and consumers demand personalization, businesses simply cannot afford to take potshots anymore. Every rupee, dollar, or euro of spend must be recovered in measurable terms.</p><p>Ironically, thus, the agency v. in‑house argument has so become so essential to businesses keen on recording growth in 2025 sustainably.</p><h2>The Case for In‑House Marketing Teams</h2><p>An in‑house marketing department is a team of employees who work directly for your business to manage branding, advertising, and digital campaigns.</p><h3>✅ In‑House Marketing Advantages</h3><p><strong>Intimate Knowledge of the Brand</strong><br/>Your employees are constantly exposed to your brand, allowing them to have great knowledge about your culture, products, and customers.</p><p><strong>Quicker Communication</strong><br/>In‑house marketers are literally a desk (or a Slack ping) away, providing quicker decision‑making and enhanced coordination.</p><p><strong>Total Control</strong><br/>Everything in their campaigns belongs to companies, such as messages and execution, and not having to wait for someone else.</p><p><strong>Cultural Synergy</strong><br/>Employees are surrounded by your brand values, so campaigns end up being consistent.</p><h3> In‑House Marketing Disadvantages</h3><p><strong>Higher Cost</strong><br/>Salaries, benefits, training, and equipment accumulate very quickly. Employing SEO experts, social, design, ads, and analytics people can be far more expensive than outsourcing.</p><p><strong>Limited Knowledge</strong><br/>A single team cannot be an expert in every category (i.e., SEO expert, performance ad, web development).</p><p><strong>Slower Adaptability</strong><br/>Adjustment for trends, tools, and algorithmic changes requires ongoing retraining — something most internal teams are not able to manage.</p><p><strong>Scaling Issues</strong><br/>Scaling campaigns typically means adding more people, which increases cost and complication.</p><h2>The Case for Bringing in a Digital Marketing Agency</h2><p>A digital marketing agency combines branding, SEO, advertising, social media, and design professionals. Instead of hiring various specialists in succession, companies purchase an array of diverse skills.</p><h3>Why Businesses Should Hire a Digital Marketing Agency like Brands Light Digital</h3><p><strong>Expertise</strong><br/>Specialist experts for every marketing field are available at Brands Light Digital — SEO specialists, PPC ad managers, and graphic designers.</p><p><strong>Affordable ROI</strong><br/>Instead of paying hundreds of employees' salary, you pay a single agency fee with a group of experts, equipment, and facilities.</p><p><strong>Scalability and Flexibility</strong><br/>Brands Light Digital campaigns scale up or down with your company's needs — without additional employees to compensate.</p><p><strong>Access to High‑Tech Tools</strong><br/>Those are technologies agencies finance in advance to buy in suites and AI‑powered ad‑optimization tech most companies can't afford to buy outright.</p><p><strong>Fresh Perspective</strong><br/>Agencies bring outside creativity and experience, setting your brand apart from the competition in a crowded market.</p><h2>ROI Comparison: In‑House vs Agency</h2><table><thead><tr><th>Factor</th><th>In‑House Team</th><th>Digital Marketing Agency (Brands Light Digital)</th></tr></thead><tbody><tr><td>Cost</td><td>High (salaries, tools, training)</td><td>Lower (single fee encompasses multiple experts &amp; tools)</td></tr><tr><td>Expertise</td><td>Limited, size dependent</td><td>Diverse, specialists across all areas</td></tr><tr><td>Scalability</td><td>Slow, must hire new</td><td>Fast, agencies can easily scale campaigns</td></tr><tr><td>Creativity</td><td>Internal‑focussed, could be stale</td><td>New external insights, trend‑focussed</td></tr><tr><td>Tools &amp; Tech</td><td>Must be invested</td><td>Included in agency partnership package</td></tr><tr><td>Speed</td><td>Quick internal decisions</td><td>Needs communication cycles</td></tr><tr><td>ROI in 2025</td><td>Moderate (budget‑dependent)</td><td>Augmented ROI with Brands Light Digital know‑how</td></tr></tbody></table><h2>Why 2025 Businesses Outsource to Brands Light Digital</h2><p>Beyond the largest of companies, budget and know‑how become impossible to mix. That's why they turn to Brands Light Digital — to offer:</p><ul><li>360° end‑to‑end marketing solutions</li><li>A complete complement of strategists, designers, and advertising professionals</li><li>ROI‑guaranteed data‑driven campaigns</li><li>Scaling strategies that scale with your expanding business</li></ul><h2>Final Verdict: Which Offers Better ROI in 2025</h2><p>Between agency model digital marketing agency ROI and in‑house teams, the choice will be dependent upon your business model.</p><p><strong>Small to Medium Businesses (SMBs):</strong> Brand Light Digital agency style will offer better ROI due to cost savings, scalability, and specialization.</p><p><strong>Enterprises:</strong> In‑house branding team with agency model generally works best.</p><p><strong>Startups:</strong> Agencies provide the fastest and cheapest way of creating momentum.</p><p>We at Brands Light Digital have assisted companies across various industries to realize greater ROI by establishing customized strategies involving creativity, analytics, and latest marketing tools. The companies that will thrive in 2025 and beyond are those which adopt a model in line with their growth agendas.</p><h2>Final Thoughts</h2><p>The in‑house vs agency debate is less about which is “better” and more about which fits your goals, budget, and vision. What’s clear is that in 2025, businesses can’t afford scattered marketing efforts — they need data‑driven strategies that deliver measurable ROI.</p><p>If you’re seeking a partner to help your brand scale smartly and maximize your marketing investment, Brands Light Digital is here to light up your growth journey.</p>"
    }
  ]}